{
  "coverage": "100%",
  "expectCount": 49,
  "actualCount": 49,
  "files": {
    "lib/App.js": {
      "expectCount": 4,
      "actualCount": 4,
      "undocumentLines": []
    },
    "lib/Node.js": {
      "expectCount": 13,
      "actualCount": 13,
      "undocumentLines": []
    },
    "lib/Request.js": {
      "expectCount": 11,
      "actualCount": 11,
      "undocumentLines": []
    },
    "lib/Response.js": {
      "expectCount": 10,
      "actualCount": 10,
      "undocumentLines": []
    },
    "lib/Route.js": {
      "expectCount": 7,
      "actualCount": 7,
      "undocumentLines": []
    },
    "lib/Router.js": {
      "expectCount": 4,
      "actualCount": 4,
      "undocumentLines": []
    }
  }
}